aiostd/__init__.py
aiostd-0.0.1.dist-info/LICENSE
aiostd-0.0.1.dist-info/METADATA
aiostd-0.0.1.dist-info/WHEEL
aiostd-0.0.1.dist-info/top_level.txt
aiostd-0.0.1.dist-info/RECORD
